opentelemetry/instrumentation/eodag/__init__.py
opentelemetry/instrumentation/eodag/metrics.py
opentelemetry/instrumentation/eodag/package.py
opentelemetry/instrumentation/eodag/tracing.py
opentelemetry_instrumentation_eodag-0.4.0.dist-info/licenses/LICENSE
opentelemetry_instrumentation_eodag-0.4.0.dist-info/licenses/NOTICE
opentelemetry_instrumentation_eodag-0.4.0.dist-info/METADATA
opentelemetry_instrumentation_eodag-0.4.0.dist-info/WHEEL
opentelemetry_instrumentation_eodag-0.4.0.dist-info/entry_points.txt
opentelemetry_instrumentation_eodag-0.4.0.dist-info/top_level.txt
opentelemetry_instrumentation_eodag-0.4.0.dist-info/RECORD
