Metadata-Version: 2.4
Name: opentelemetry-instrumentation-eodag
Version: 0.4.0
Summary: OpenTelemetry EODAG Instrumentation
Author-email: CS GROUP - France <eodag@csgroup.space>
License: 
Project-URL: Homepage, https://github.com/CS-SI/opentelemetry-instrumentation-eodag
Project-URL: Repository, https://github.com/CS-SI/opentelemetry-instrumentation-eodag
Project-URL: Issues, https://github.com/CS-SI/opentelemetry-instrumentation-eodag/issues/
Requires-Python: >=3.9
License-File: LICENSE
License-File: NOTICE
Requires-Dist: eodag
Requires-Dist: opentelemetry-api
Requires-Dist: opentelemetry-sdk
Provides-Extra: dev
Requires-Dist: pre-commit; extra == "dev"
Requires-Dist: pytest; extra == "dev"
Requires-Dist: pytest-cov; extra == "dev"
Requires-Dist: pytest-html; extra == "dev"
Requires-Dist: pytest-xdist; extra == "dev"
Requires-Dist: pytest-socket; extra == "dev"
Requires-Dist: pytest-instafail; extra == "dev"
Requires-Dist: tox; extra == "dev"
Requires-Dist: tox-uv; extra == "dev"
Requires-Dist: twine; extra == "dev"
Requires-Dist: wheel; extra == "dev"
Dynamic: license-file
